PyMusic_Player.py
PyMusic_Player111-0.0.1.dist-info/LICENSE
PyMusic_Player111-0.0.1.dist-info/METADATA
PyMusic_Player111-0.0.1.dist-info/WHEEL
PyMusic_Player111-0.0.1.dist-info/top_level.txt
PyMusic_Player111-0.0.1.dist-info/RECORD
